affection.py
affection-0.1.1.dist-info/WHEEL
affection-0.1.1.dist-info/METADATA
affection-0.1.1.dist-info/license_files/LICENSE
affection-0.1.1.dist-info/RECORD
