Metadata-Version: 2.1
Name: affection
Version: 0.1.1
Summary: Algebraic Effect for modern Python.
License: MIT
Author-email: BlueGlassBlock <blueglassblock@outlook.com>
Requires-Python: >=3.7, <4.0
Requires-Dist: typing-extensions~=4.3
